lumi/__init__.py
lumi/__main__.py
lumi/ding.mp3
lumi/dong.mp3
lumi/s2t.py
lumi/transcribe.py
lumi/cli/__init__.py
lumi/cli/s2t_cli.py
lumi_ai-0.1.2.dist-info/METADATA
lumi_ai-0.1.2.dist-info/WHEEL
lumi_ai-0.1.2.dist-info/entry_points.txt
lumi_ai-0.1.2.dist-info/top_level.txt
lumi_ai-0.1.2.dist-info/RECORD
