Metadata-Version: 2.2
Name: lumi-ai
Version: 0.1.2
Summary: Speech-to-text utility with hotkey activation
Author: Lumi Developers
License: MIT
Classifier: Programming Language :: Python :: 3
Classifier: License :: OSI Approved :: MIT License
Classifier: Operating System :: MacOS
Classifier: Topic :: Utilities
Classifier: Intended Audience :: End Users/Desktop
Requires-Python: >=3.12
Requires-Dist: elevenlabs>=1.52.0
Requires-Dist: groq>=0.18.0
Requires-Dist: mlx-whisper>=0.4.2
Requires-Dist: nava>=0.7
Requires-Dist: pyaudio>=0.2.14
Requires-Dist: pynput>=1.7.7
Requires-Dist: pyperclip>=1.9.0
Requires-Dist: requests>=2.32.3
Provides-Extra: dev
Requires-Dist: pytest>=8.3.4; extra == "dev"
Requires-Dist: ruff>=0.9.8; extra == "dev"
